LICENSE.txt
README.rst
license.txt
setup.cfg
setup.py
src/Unum.egg-info/PKG-INFO
src/Unum.egg-info/SOURCES.txt
src/Unum.egg-info/dependency_links.txt
src/Unum.egg-info/top_level.txt
src/tests/__init__.py
src/unum/__init__.py
src/unum/units/__init__.py
src/unum/units/custom/__init__.py
src/unum/units/others/__init__.py
src/unum/units/si/__init__.py
src/unum/units/si/base.py
src/unum/units/si/derived.py