Metadata-Version: 2.1
Name: Unum
Version: 4.2.1
Summary: Units in Python
Home-page: https://unum.readthedocs.io/
Author: Chris MacLeod, Pierre Denis, Lukasz Laba
Author-email: lukaszlaba@gmail.com
License: GNU General Public License (GPL)
Keywords: si units,calculations,math,unit system
Platform: UNKNOWN
Classifier: Development Status :: 5 - Production/Stable
Classifier: Intended Audience :: Science/Research
Classifier: Intended Audience :: Developers
Classifier: License :: OSI Approved :: GNU General Public License (GPL)
Classifier: Operating System :: POSIX :: Linux
Classifier: Operating System :: Microsoft :: Windows
Classifier: Programming Language :: Python
Classifier: Topic :: Scientific/Engineering
Classifier: Topic :: Scientific/Engineering :: Mathematics
Classifier: Topic :: Scientific/Engineering :: Physics
Classifier: Topic :: Education
Requires-Python: >=2.4, <4
License-File: LICENSE.txt
